[{
  "_id": 143720,
  "totalCount": 79
},
{
  "_id": 744624,
  "totalCount": 91
},
{
  "_id": 917549,
  "totalCount": 55
},
{
  "_id": 969836,
  "totalCount": 85
},
{
  "_id": 547625,
  "totalCount": 86
},
{
  "_id": 949471,
  "totalCount": 74
},
{
  "_id": 820176,
  "totalCount": 96
},
{
  "_id": 540341,
  "totalCount": 59
},
{
  "_id": 330318,
  "totalCount": 72
},
{
  "_id": 413293,
  "totalCount": 67
},
{
  "_id": 261796,
  "totalCount": 54
},
{
  "_id": 836981,
  "totalCount": 89
},
{
  "_id": 999137,
  "totalCount": 93
},
{
  "_id": 260799,
  "totalCount": 92
},
{
  "_id": 719393,
  "totalCount": 98
},
{
  "_id": 238139,
  "totalCount": 99
},
{
  "_id": 626536,
  "totalCount": 74
},
{
  "_id": 619693,
  "totalCount": 66
},
{
  "_id": 611752,
  "totalCount": 70
},
{
  "_id": 445713,
  "totalCount": 58
},
{
  "_id": 208252,
  "totalCount": 58
},
{
  "_id": 66698,
  "totalCount": 75
},
{
  "_id": 604732,
  "totalCount": 74
},
{
  "_id": 870466,
  "totalCount": 92
},
{
  "_id": 89646,
  "totalCount": 86
},
{
  "_id": 264514,
  "totalCount": 95
},
{
  "_id": 979257,
  "totalCount": 61
},
{
  "_id": 544598,
  "totalCount": 64
},
{
  "_id": 951500,
  "totalCount": 77
},
{
  "_id": 130832,
  "totalCount": 75
},
{
  "_id": 418570,
  "totalCount": 93
},
{
  "_id": 833631,
  "totalCount": 90
},
{
  "_id": 437245,
  "totalCount": 81
},
{
  "_id": 146621,
  "totalCount": 79
},
{
  "_id": 158557,
  "totalCount": 80
},
{
  "_id": 879735,
  "totalCount": 60
},
{
  "_id": 632807,
  "totalCount": 100
},
{
  "_id": 718678,
  "totalCount": 72
},
{
  "_id": 475604,
  "totalCount": 74
},
{
  "_id": 795756,
  "totalCount": 96
},
{
  "_id": 798380,
  "totalCount": 94
},
{
  "_id": 755845,
  "totalCount": 59
},
{
  "_id": 880595,
  "totalCount": 100
},
{
  "_id": 377923,
  "totalCount": 92
},
{
  "_id": 602143,
  "totalCount": 89
},
{
  "_id": 657111,
  "totalCount": 63
},
{
  "_id": 343230,
  "totalCount": 98
},
{
  "_id": 133163,
  "totalCount": 73
},
{
  "_id": 646815,
  "totalCount": 68
},
{
  "_id": 616040,
  "totalCount": 98
},
{
  "_id": 620350,
  "totalCount": 69
},
{
  "_id": 436380,
  "totalCount": 82
},
{
  "_id": 379691,
  "totalCount": 92
},
{
  "_id": 448816,
  "totalCount": 52
},
{
  "_id": 578413,
  "totalCount": 76
},
{
  "_id": 830030,
  "totalCount": 86
},
{
  "_id": 779716,
  "totalCount": 57
},
{
  "_id": 103346,
  "totalCount": 70
},
{
  "_id": 51645,
  "totalCount": 71
},
{
  "_id": 769877,
  "totalCount": 81
},
{
  "_id": 452778,
  "totalCount": 63
},
{
  "_id": 995007,
  "totalCount": 62
},
{
  "_id": 271625,
  "totalCount": 74
},
{
  "_id": 668634,
  "totalCount": 78
},
{
  "_id": 698900,
  "totalCount": 66
},
{
  "_id": 278149,
  "totalCount": 77
},
{
  "_id": 153224,
  "totalCount": 99
},
{
  "_id": 599670,
  "totalCount": 82
},
{
  "_id": 410867,
  "totalCount": 89
},
{
  "_id": 776263,
  "totalCount": 80
},
{
  "_id": 384335,
  "totalCount": 57
},
{
  "_id": 635410,
  "totalCount": 73
},
{
  "_id": 445672,
  "totalCount": 54
},
{
  "_id": 565763,
  "totalCount": 56
},
{
  "_id": 183917,
  "totalCount": 94
},
{
  "_id": 774823,
  "totalCount": 98
},
{
  "_id": 895735,
  "totalCount": 81
},
{
  "_id": 124603,
  "totalCount": 98
},
{
  "_id": 246018,
  "totalCount": 74
},
{
  "_id": 345766,
  "totalCount": 83
},
{
  "_id": 328304,
  "totalCount": 62
},
{
  "_id": 82467,
  "totalCount": 85
},
{
  "_id": 881867,
  "totalCount": 84
},
{
  "_id": 602559,
  "totalCount": 78
},
{
  "_id": 486766,
  "totalCount": 90
},
{
  "_id": 739622,
  "totalCount": 61
},
{
  "_id": 837602,
  "totalCount": 93
},
{
  "_id": 741762,
  "totalCount": 69
},
{
  "_id": 765101,
  "totalCount": 65
},
{
  "_id": 702924,
  "totalCount": 55
},
{
  "_id": 738278,
  "totalCount": 74
},
{
  "_id": 727418,
  "totalCount": 87
},
{
  "_id": 147641,
  "totalCount": 72
},
{
  "_id": 123689,
  "totalCount": 52
},
{
  "_id": 181687,
  "totalCount": 76
},
{
  "_id": 968012,
  "totalCount": 83
},
{
  "_id": 374953,
  "totalCount": 58
},
{
  "_id": 332256,
  "totalCount": 63
},
{
  "_id": 727330,
  "totalCount": 60
},
{
  "_id": 945232,
  "totalCount": 52
},
{
  "_id": 514049,
  "totalCount": 65
},
{
  "_id": 278497,
  "totalCount": 79
},
{
  "_id": 404183,
  "totalCount": 76
},
{
  "_id": 621061,
  "totalCount": 71
},
{
  "_id": 690308,
  "totalCount": 66
},
{
  "_id": 692070,
  "totalCount": 80
},
{
  "_id": 90414,
  "totalCount": 94
},
{
  "_id": 401997,
  "totalCount": 85
},
{
  "_id": 202669,
  "totalCount": 61
},
{
  "_id": 753126,
  "totalCount": 60
},
{
  "_id": 347967,
  "totalCount": 92
},
{
  "_id": 260499,
  "totalCount": 94
},
{
  "_id": 434948,
  "totalCount": 89
},
{
  "_id": 249078,
  "totalCount": 89
},
{
  "_id": 999198,
  "totalCount": 99
},
{
  "_id": 257801,
  "totalCount": 75
},
{
  "_id": 667074,
  "totalCount": 96
},
{
  "_id": 628472,
  "totalCount": 57
},
{
  "_id": 615886,
  "totalCount": 58
},
{
  "_id": 643169,
  "totalCount": 80
},
{
  "_id": 706316,
  "totalCount": 56
},
{
  "_id": 696619,
  "totalCount": 91
},
{
  "_id": 973057,
  "totalCount": 99
},
{
  "_id": 94177,
  "totalCount": 77
},
{
  "_id": 987387,
  "totalCount": 85
},
{
  "_id": 770262,
  "totalCount": 90
},
{
  "_id": 144469,
  "totalCount": 51
},
{
  "_id": 280867,
  "totalCount": 83
},
{
  "_id": 577112,
  "totalCount": 56
},
{
  "_id": 700611,
  "totalCount": 68
},
{
  "_id": 761387,
  "totalCount": 65
},
{
  "_id": 66589,
  "totalCount": 57
},
{
  "_id": 552174,
  "totalCount": 54
},
{
  "_id": 674433,
  "totalCount": 79
},
{
  "_id": 371264,
  "totalCount": 86
},
{
  "_id": 461657,
  "totalCount": 80
},
{
  "_id": 76339,
  "totalCount": 52
},
{
  "_id": 122923,
  "totalCount": 53
},
{
  "_id": 839927,
  "totalCount": 75
},
{
  "_id": 909802,
  "totalCount": 75
},
{
  "_id": 572981,
  "totalCount": 83
},
{
  "_id": 842570,
  "totalCount": 66
},
{
  "_id": 454289,
  "totalCount": 62
},
{
  "_id": 235824,
  "totalCount": 93
},
{
  "_id": 238373,
  "totalCount": 84
},
{
  "_id": 823908,
  "totalCount": 84
},
{
  "_id": 678737,
  "totalCount": 82
},
{
  "_id": 187107,
  "totalCount": 96
},
{
  "_id": 461793,
  "totalCount": 51
},
{
  "_id": 730522,
  "totalCount": 81
},
{
  "_id": 353465,
  "totalCount": 74
},
{
  "_id": 551774,
  "totalCount": 75
},
{
  "_id": 291224,
  "totalCount": 67
},
{
  "_id": 831600,
  "totalCount": 77
},
{
  "_id": 303316,
  "totalCount": 99
},
{
  "_id": 207715,
  "totalCount": 87
},
{
  "_id": 674364,
  "totalCount": 57
},
{
  "_id": 299100,
  "totalCount": 52
},
{
  "_id": 425815,
  "totalCount": 62
},
{
  "_id": 540237,
  "totalCount": 76
},
{
  "_id": 802298,
  "totalCount": 81
},
{
  "_id": 528224,
  "totalCount": 89
},
{
  "_id": 428217,
  "totalCount": 88
},
{
  "_id": 754737,
  "totalCount": 55
},
{
  "_id": 126092,
  "totalCount": 74
},
{
  "_id": 518420,
  "totalCount": 59
},
{
  "_id": 813925,
  "totalCount": 99
},
{
  "_id": 531370,
  "totalCount": 56
},
{
  "_id": 985280,
  "totalCount": 69
},
{
  "_id": 827328,
  "totalCount": 67
},
{
  "_id": 681381,
  "totalCount": 52
},
{
  "_id": 201361,
  "totalCount": 71
},
{
  "_id": 126444,
  "totalCount": 76
},
{
  "_id": 781775,
  "totalCount": 93
},
{
  "_id": 525530,
  "totalCount": 89
},
{
  "_id": 951840,
  "totalCount": 97
},
{
  "_id": 111287,
  "totalCount": 63
},
{
  "_id": 58303,
  "totalCount": 60
},
{
  "_id": 691917,
  "totalCount": 64
},
{
  "_id": 344107,
  "totalCount": 90
},
{
  "_id": 996624,
  "totalCount": 73
},
{
  "_id": 57322,
  "totalCount": 79
},
{
  "_id": 433296,
  "totalCount": 55
},
{
  "_id": 611998,
  "totalCount": 64
},
{
  "_id": 331043,
  "totalCount": 98
},
{
  "_id": 360322,
  "totalCount": 71
},
{
  "_id": 595585,
  "totalCount": 51
},
{
  "_id": 311880,
  "totalCount": 97
},
{
  "_id": 384574,
  "totalCount": 65
},
{
  "_id": 236908,
  "totalCount": 95
},
{
  "_id": 151378,
  "totalCount": 51
},
{
  "_id": 661661,
  "totalCount": 95
},
{
  "_id": 436291,
  "totalCount": 63
},
{
  "_id": 768386,
  "totalCount": 82
},
{
  "_id": 236337,
  "totalCount": 75
},
{
  "_id": 602560,
  "totalCount": 59
},
{
  "_id": 280906,
  "totalCount": 87
},
{
  "_id": 198100,
  "totalCount": 66
},
{
  "_id": 645476,
  "totalCount": 66
},
{
  "_id": 105134,
  "totalCount": 88
},
{
  "_id": 129971,
  "totalCount": 61
},
{
  "_id": 109478,
  "totalCount": 67
},
{
  "_id": 92217,
  "totalCount": 68
},
{
  "_id": 910860,
  "totalCount": 86
},
{
  "_id": 178000,
  "totalCount": 68
},
{
  "_id": 498050,
  "totalCount": 62
},
{
  "_id": 131201,
  "totalCount": 54
},
{
  "_id": 485840,
  "totalCount": 57
},
{
  "_id": 642554,
  "totalCount": 94
},
{
  "_id": 505367,
  "totalCount": 54
},
{
  "_id": 771691,
  "totalCount": 86
},
{
  "_id": 655073,
  "totalCount": 74
},
{
  "_id": 525945,
  "totalCount": 92
},
{
  "_id": 570818,
  "totalCount": 73
},
{
  "_id": 328627,
  "totalCount": 85
},
{
  "_id": 907816,
  "totalCount": 76
},
{
  "_id": 117971,
  "totalCount": 92
},
{
  "_id": 588722,
  "totalCount": 69
},
{
  "_id": 248380,
  "totalCount": 73
},
{
  "_id": 576395,
  "totalCount": 80
},
{
  "_id": 718470,
  "totalCount": 88
},
{
  "_id": 816481,
  "totalCount": 93
},
{
  "_id": 351402,
  "totalCount": 63
},
{
  "_id": 963591,
  "totalCount": 86
},
{
  "_id": 534789,
  "totalCount": 64
},
{
  "_id": 120556,
  "totalCount": 75
},
{
  "_id": 255267,
  "totalCount": 57
},
{
  "_id": 105098,
  "totalCount": 51
},
{
  "_id": 475387,
  "totalCount": 83
},
{
  "_id": 831097,
  "totalCount": 99
},
{
  "_id": 720370,
  "totalCount": 65
},
{
  "_id": 333075,
  "totalCount": 52
},
{
  "_id": 565145,
  "totalCount": 66
},
{
  "_id": 719203,
  "totalCount": 97
},
{
  "_id": 275355,
  "totalCount": 99
},
{
  "_id": 244662,
  "totalCount": 67
},
{
  "_id": 809938,
  "totalCount": 59
},
{
  "_id": 731206,
  "totalCount": 52
},
{
  "_id": 489563,
  "totalCount": 69
},
{
  "_id": 331169,
  "totalCount": 58
},
{
  "_id": 489178,
  "totalCount": 81
},
{
  "_id": 304730,
  "totalCount": 78
},
{
  "_id": 140557,
  "totalCount": 92
},
{
  "_id": 650729,
  "totalCount": 55
},
{
  "_id": 626807,
  "totalCount": 71
},
{
  "_id": 571880,
  "totalCount": 65
},
{
  "_id": 679340,
  "totalCount": 82
},
{
  "_id": 923468,
  "totalCount": 91
},
{
  "_id": 614544,
  "totalCount": 94
},
{
  "_id": 209755,
  "totalCount": 85
},
{
  "_id": 887464,
  "totalCount": 95
},
{
  "_id": 453177,
  "totalCount": 89
},
{
  "_id": 890055,
  "totalCount": 52
},
{
  "_id": 233104,
  "totalCount": 70
},
{
  "_id": 394725,
  "totalCount": 61
},
{
  "_id": 984021,
  "totalCount": 84
},
{
  "_id": 183253,
  "totalCount": 66
},
{
  "_id": 487188,
  "totalCount": 73
},
{
  "_id": 79999,
  "totalCount": 71
},
{
  "_id": 675420,
  "totalCount": 100
},
{
  "_id": 206062,
  "totalCount": 87
},
{
  "_id": 86373,
  "totalCount": 54
},
{
  "_id": 568852,
  "totalCount": 78
},
{
  "_id": 965232,
  "totalCount": 80
},
{
  "_id": 826367,
  "totalCount": 76
},
{
  "_id": 155327,
  "totalCount": 87
},
{
  "_id": 426231,
  "totalCount": 56
},
{
  "_id": 617243,
  "totalCount": 79
},
{
  "_id": 587875,
  "totalCount": 77
},
{
  "_id": 473748,
  "totalCount": 63
},
{
  "_id": 976027,
  "totalCount": 54
},
{
  "_id": 640540,
  "totalCount": 58
},
{
  "_id": 235687,
  "totalCount": 83
},
{
  "_id": 932908,
  "totalCount": 55
},
{
  "_id": 688134,
  "totalCount": 97
},
{
  "_id": 808642,
  "totalCount": 77
},
{
  "_id": 874342,
  "totalCount": 93
},
{
  "_id": 702610,
  "totalCount": 52
},
{
  "_id": 310074,
  "totalCount": 60
},
{
  "_id": 154636,
  "totalCount": 76
},
{
  "_id": 409753,
  "totalCount": 70
},
{
  "_id": 90019,
  "totalCount": 71
},
{
  "_id": 89698,
  "totalCount": 86
},
{
  "_id": 380860,
  "totalCount": 74
},
{
  "_id": 242287,
  "totalCount": 58
},
{
  "_id": 700899,
  "totalCount": 82
},
{
  "_id": 486521,
  "totalCount": 55
},
{
  "_id": 981821,
  "totalCount": 53
},
{
  "_id": 304914,
  "totalCount": 65
},
{
  "_id": 523409,
  "totalCount": 53
},
{
  "_id": 243963,
  "totalCount": 61
},
{
  "_id": 498251,
  "totalCount": 72
},
{
  "_id": 674880,
  "totalCount": 79
},
{
  "_id": 443178,
  "totalCount": 66
},
{
  "_id": 972041,
  "totalCount": 70
},
{
  "_id": 565989,
  "totalCount": 92
},
{
  "_id": 516709,
  "totalCount": 63
},
{
  "_id": 249109,
  "totalCount": 58
},
{
  "_id": 846855,
  "totalCount": 60
},
{
  "_id": 656564,
  "totalCount": 95
},
{
  "_id": 964645,
  "totalCount": 88
},
{
  "_id": 894663,
  "totalCount": 56
},
{
  "_id": 232492,
  "totalCount": 70
},
{
  "_id": 881765,
  "totalCount": 85
},
{
  "_id": 960469,
  "totalCount": 93
},
{
  "_id": 714727,
  "totalCount": 79
},
{
  "_id": 402535,
  "totalCount": 97
},
{
  "_id": 701602,
  "totalCount": 99
},
{
  "_id": 483041,
  "totalCount": 57
},
{
  "_id": 369055,
  "totalCount": 64
},
{
  "_id": 630132,
  "totalCount": 95
},
{
  "_id": 235286,
  "totalCount": 83
},
{
  "_id": 506711,
  "totalCount": 72
},
{
  "_id": 906796,
  "totalCount": 96
},
{
  "_id": 471113,
  "totalCount": 76
},
{
  "_id": 77032,
  "totalCount": 81
},
{
  "_id": 785013,
  "totalCount": 79
},
{
  "_id": 233540,
  "totalCount": 67
},
{
  "_id": 704067,
  "totalCount": 54
},
{
  "_id": 481754,
  "totalCount": 69
},
{
  "_id": 633630,
  "totalCount": 66
},
{
  "_id": 694827,
  "totalCount": 86
},
{
  "_id": 561206,
  "totalCount": 62
},
{
  "_id": 466310,
  "totalCount": 90
},
{
  "_id": 941541,
  "totalCount": 83
},
{
  "_id": 627788,
  "totalCount": 54
},
{
  "_id": 397774,
  "totalCount": 54
},
{
  "_id": 222581,
  "totalCount": 60
},
{
  "_id": 998674,
  "totalCount": 70
},
{
  "_id": 120548,
  "totalCount": 63
},
{
  "_id": 917660,
  "totalCount": 78
},
{
  "_id": 292277,
  "totalCount": 70
},
{
  "_id": 134905,
  "totalCount": 58
},
{
  "_id": 912504,
  "totalCount": 51
},
{
  "_id": 557378,
  "totalCount": 56
},
{
  "_id": 958881,
  "totalCount": 96
},
{
  "_id": 572114,
  "totalCount": 77
},
{
  "_id": 996263,
  "totalCount": 77
},
{
  "_id": 881767,
  "totalCount": 63
},
{
  "_id": 147334,
  "totalCount": 77
},
{
  "_id": 329562,
  "totalCount": 99
},
{
  "_id": 703331,
  "totalCount": 57
},
{
  "_id": 228290,
  "totalCount": 66
},
{
  "_id": 733568,
  "totalCount": 54
},
{
  "_id": 722342,
  "totalCount": 54
},
{
  "_id": 598715,
  "totalCount": 78
},
{
  "_id": 87409,
  "totalCount": 75
},
{
  "_id": 872805,
  "totalCount": 97
},
{
  "_id": 617621,
  "totalCount": 89
},
{
  "_id": 420660,
  "totalCount": 55
},
{
  "_id": 953567,
  "totalCount": 90
},
{
  "_id": 225728,
  "totalCount": 71
},
{
  "_id": 707812,
  "totalCount": 98
},
{
  "_id": 956881,
  "totalCount": 91
},
{
  "_id": 889573,
  "totalCount": 72
},
{
  "_id": 222322,
  "totalCount": 53
},
{
  "_id": 616805,
  "totalCount": 89
},
{
  "_id": 472963,
  "totalCount": 84
},
{
  "_id": 462528,
  "totalCount": 82
},
{
  "_id": 317282,
  "totalCount": 77
},
{
  "_id": 798739,
  "totalCount": 64
},
{
  "_id": 855373,
  "totalCount": 58
},
{
  "_id": 625263,
  "totalCount": 51
},
{
  "_id": 501408,
  "totalCount": 74
},
{
  "_id": 82008,
  "totalCount": 66
},
{
  "_id": 377488,
  "totalCount": 88
},
{
  "_id": 921629,
  "totalCount": 62
},
{
  "_id": 564812,
  "totalCount": 75
},
{
  "_id": 558864,
  "totalCount": 63
},
{
  "_id": 788678,
  "totalCount": 64
},
{
  "_id": 523507,
  "totalCount": 65
},
{
  "_id": 866159,
  "totalCount": 73
},
{
  "_id": 412203,
  "totalCount": 60
},
{
  "_id": 323327,
  "totalCount": 54
},
{
  "_id": 134434,
  "totalCount": 100
},
{
  "_id": 584594,
  "totalCount": 75
},
{
  "_id": 483220,
  "totalCount": 97
},
{
  "_id": 576646,
  "totalCount": 61
},
{
  "_id": 870933,
  "totalCount": 54
},
{
  "_id": 657218,
  "totalCount": 85
},
{
  "_id": 340147,
  "totalCount": 82
},
{
  "_id": 619619,
  "totalCount": 100
},
{
  "_id": 205563,
  "totalCount": 57
},
{
  "_id": 423171,
  "totalCount": 92
},
{
  "_id": 853542,
  "totalCount": 51
},
{
  "_id": 321695,
  "totalCount": 92
},
{
  "_id": 351206,
  "totalCount": 77
},
{
  "_id": 935353,
  "totalCount": 86
},
{
  "_id": 437371,
  "totalCount": 81
},
{
  "_id": 348140,
  "totalCount": 97
},
{
  "_id": 904260,
  "totalCount": 60
},
{
  "_id": 678779,
  "totalCount": 76
},
{
  "_id": 581892,
  "totalCount": 74
},
{
  "_id": 144876,
  "totalCount": 53
},
{
  "_id": 235779,
  "totalCount": 77
},
{
  "_id": 303025,
  "totalCount": 97
},
{
  "_id": 430152,
  "totalCount": 55
},
{
  "_id": 141586,
  "totalCount": 96
},
{
  "_id": 228298,
  "totalCount": 83
},
{
  "_id": 606333,
  "totalCount": 99
},
{
  "_id": 519072,
  "totalCount": 76
},
{
  "_id": 730824,
  "totalCount": 69
},
{
  "_id": 308785,
  "totalCount": 67
},
{
  "_id": 145588,
  "totalCount": 84
},
{
  "_id": 541119,
  "totalCount": 69
},
{
  "_id": 814901,
  "totalCount": 60
},
{
  "_id": 87965,
  "totalCount": 58
},
{
  "_id": 964253,
  "totalCount": 65
},
{
  "_id": 980056,
  "totalCount": 73
},
{
  "_id": 996840,
  "totalCount": 74
},
{
  "_id": 333315,
  "totalCount": 68
},
{
  "_id": 883283,
  "totalCount": 59
},
{
  "_id": 745392,
  "totalCount": 53
},
{
  "_id": 327942,
  "totalCount": 55
},
{
  "_id": 419542,
  "totalCount": 89
},
{
  "_id": 691022,
  "totalCount": 77
},
{
  "_id": 394038,
  "totalCount": 90
},
{
  "_id": 990274,
  "totalCount": 55
},
{
  "_id": 814989,
  "totalCount": 52
},
{
  "_id": 682405,
  "totalCount": 69
},
{
  "_id": 814632,
  "totalCount": 93
},
{
  "_id": 898675,
  "totalCount": 62
},
{
  "_id": 729752,
  "totalCount": 94
},
{
  "_id": 904434,
  "totalCount": 84
},
{
  "_id": 294632,
  "totalCount": 92
},
{
  "_id": 122551,
  "totalCount": 68
},
{
  "_id": 297499,
  "totalCount": 87
},
{
  "_id": 153377,
  "totalCount": 90
},
{
  "_id": 679236,
  "totalCount": 66
},
{
  "_id": 531283,
  "totalCount": 90
},
{
  "_id": 720906,
  "totalCount": 96
},
{
  "_id": 906770,
  "totalCount": 67
},
{
  "_id": 96021,
  "totalCount": 56
},
{
  "_id": 929644,
  "totalCount": 73
},
{
  "_id": 712597,
  "totalCount": 89
},
{
  "_id": 825051,
  "totalCount": 89
},
{
  "_id": 918539,
  "totalCount": 97
},
{
  "_id": 667014,
  "totalCount": 58
},
{
  "_id": 122908,
  "totalCount": 56
},
{
  "_id": 77690,
  "totalCount": 90
},
{
  "_id": 385319,
  "totalCount": 67
},
{
  "_id": 544701,
  "totalCount": 58
},
{
  "_id": 412107,
  "totalCount": 79
},
{
  "_id": 214649,
  "totalCount": 58
},
{
  "_id": 199407,
  "totalCount": 97
},
{
  "_id": 387979,
  "totalCount": 95
},
{
  "_id": 609817,
  "totalCount": 70
},
{
  "_id": 296866,
  "totalCount": 96
},
{
  "_id": 814687,
  "totalCount": 72
},
{
  "_id": 56045,
  "totalCount": 69
},
{
  "_id": 971879,
  "totalCount": 86
},
{
  "_id": 861706,
  "totalCount": 72
},
{
  "_id": 729049,
  "totalCount": 76
},
{
  "_id": 87437,
  "totalCount": 82
},
{
  "_id": 499796,
  "totalCount": 88
},
{
  "_id": 96431,
  "totalCount": 99
},
{
  "_id": 211992,
  "totalCount": 61
},
{
  "_id": 584619,
  "totalCount": 70
},
{
  "_id": 570536,
  "totalCount": 82
},
{
  "_id": 918103,
  "totalCount": 75
},
{
  "_id": 572301,
  "totalCount": 67
},
{
  "_id": 947606,
  "totalCount": 78
},
{
  "_id": 146967,
  "totalCount": 80
},
{
  "_id": 492843,
  "totalCount": 97
},
{
  "_id": 952666,
  "totalCount": 66
},
{
  "_id": 849780,
  "totalCount": 72
},
{
  "_id": 384111,
  "totalCount": 74
},
{
  "_id": 225511,
  "totalCount": 59
},
{
  "_id": 635650,
  "totalCount": 98
},
{
  "_id": 878471,
  "totalCount": 93
},
{
  "_id": 565468,
  "totalCount": 81
},
{
  "_id": 485390,
  "totalCount": 51
},
{
  "_id": 591359,
  "totalCount": 88
},
{
  "_id": 534355,
  "totalCount": 81
},
{
  "_id": 505282,
  "totalCount": 65
},
{
  "_id": 199711,
  "totalCount": 69
},
{
  "_id": 413410,
  "totalCount": 96
},
{
  "_id": 184422,
  "totalCount": 52
},
{
  "_id": 317449,
  "totalCount": 53
},
{
  "_id": 509894,
  "totalCount": 76
},
{
  "_id": 851625,
  "totalCount": 84
},
{
  "_id": 859284,
  "totalCount": 87
},
{
  "_id": 684319,
  "totalCount": 97
},
{
  "_id": 170945,
  "totalCount": 66
},
{
  "_id": 59715,
  "totalCount": 93
},
{
  "_id": 678107,
  "totalCount": 95
},
{
  "_id": 305286,
  "totalCount": 80
},
{
  "_id": 508452,
  "totalCount": 77
},
{
  "_id": 637895,
  "totalCount": 62
},
{
  "_id": 642929,
  "totalCount": 63
},
{
  "_id": 559866,
  "totalCount": 98
},
{
  "_id": 520970,
  "totalCount": 74
},
{
  "_id": 882090,
  "totalCount": 92
},
{
  "_id": 118134,
  "totalCount": 72
},
{
  "_id": 313926,
  "totalCount": 89
},
{
  "_id": 139582,
  "totalCount": 93
},
{
  "_id": 712356,
  "totalCount": 87
},
{
  "_id": 932130,
  "totalCount": 95
},
{
  "_id": 240640,
  "totalCount": 97
},
{
  "_id": 162819,
  "totalCount": 75
},
{
  "_id": 803669,
  "totalCount": 96
},
{
  "_id": 842047,
  "totalCount": 55
},
{
  "_id": 514695,
  "totalCount": 69
},
{
  "_id": 789739,
  "totalCount": 66
},
{
  "_id": 518243,
  "totalCount": 65
},
{
  "_id": 627629,
  "totalCount": 90
},
{
  "_id": 571279,
  "totalCount": 67
},
{
  "_id": 238662,
  "totalCount": 86
},
{
  "_id": 506845,
  "totalCount": 94
},
{
  "_id": 51617,
  "totalCount": 100
},
{
  "_id": 692687,
  "totalCount": 90
},
{
  "_id": 992173,
  "totalCount": 91
},
{
  "_id": 358684,
  "totalCount": 67
},
{
  "_id": 902818,
  "totalCount": 82
},
{
  "_id": 267252,
  "totalCount": 75
},
{
  "_id": 618333,
  "totalCount": 94
},
{
  "_id": 934872,
  "totalCount": 54
},
{
  "_id": 147085,
  "totalCount": 94
},
{
  "_id": 980440,
  "totalCount": 90
},
{
  "_id": 211212,
  "totalCount": 56
},
{
  "_id": 604215,
  "totalCount": 95
},
{
  "_id": 101920,
  "totalCount": 59
},
{
  "_id": 111626,
  "totalCount": 64
},
{
  "_id": 617210,
  "totalCount": 71
},
{
  "_id": 387877,
  "totalCount": 92
},
{
  "_id": 84115,
  "totalCount": 75
},
{
  "_id": 391838,
  "totalCount": 67
},
{
  "_id": 825576,
  "totalCount": 95
},
{
  "_id": 181073,
  "totalCount": 56
},
{
  "_id": 977774,
  "totalCount": 98
},
{
  "_id": 150713,
  "totalCount": 54
},
{
  "_id": 168924,
  "totalCount": 53
},
{
  "_id": 726384,
  "totalCount": 74
},
{
  "_id": 375486,
  "totalCount": 97
},
{
  "_id": 906290,
  "totalCount": 57
},
{
  "_id": 935752,
  "totalCount": 56
},
{
  "_id": 966314,
  "totalCount": 97
},
{
  "_id": 537158,
  "totalCount": 93
},
{
  "_id": 433314,
  "totalCount": 79
},
{
  "_id": 70492,
  "totalCount": 75
},
{
  "_id": 994208,
  "totalCount": 83
},
{
  "_id": 987709,
  "totalCount": 68
},
{
  "_id": 51253,
  "totalCount": 53
},
{
  "_id": 185104,
  "totalCount": 58
},
{
  "_id": 386971,
  "totalCount": 85
},
{
  "_id": 159243,
  "totalCount": 80
},
{
  "_id": 660047,
  "totalCount": 69
},
{
  "_id": 752970,
  "totalCount": 90
},
{
  "_id": 849766,
  "totalCount": 87
},
{
  "_id": 245503,
  "totalCount": 90
},
{
  "_id": 131176,
  "totalCount": 54
},
{
  "_id": 851242,
  "totalCount": 72
},
{
  "_id": 569420,
  "totalCount": 52
},
{
  "_id": 546681,
  "totalCount": 98
},
{
  "_id": 943710,
  "totalCount": 79
},
{
  "_id": 997433,
  "totalCount": 55
},
{
  "_id": 459185,
  "totalCount": 62
},
{
  "_id": 309490,
  "totalCount": 61
},
{
  "_id": 59275,
  "totalCount": 79
},
{
  "_id": 460439,
  "totalCount": 89
},
{
  "_id": 644474,
  "totalCount": 73
},
{
  "_id": 585228,
  "totalCount": 78
},
{
  "_id": 991663,
  "totalCount": 89
},
{
  "_id": 859697,
  "totalCount": 77
},
{
  "_id": 130610,
  "totalCount": 57
},
{
  "_id": 596107,
  "totalCount": 58
},
{
  "_id": 986196,
  "totalCount": 70
},
{
  "_id": 356905,
  "totalCount": 88
},
{
  "_id": 137994,
  "totalCount": 65
},
{
  "_id": 795040,
  "totalCount": 74
},
{
  "_id": 686986,
  "totalCount": 60
},
{
  "_id": 76399,
  "totalCount": 53
},
{
  "_id": 266920,
  "totalCount": 70
},
{
  "_id": 734321,
  "totalCount": 72
},
{
  "_id": 511276,
  "totalCount": 96
},
{
  "_id": 708669,
  "totalCount": 72
},
{
  "_id": 717404,
  "totalCount": 64
},
{
  "_id": 429119,
  "totalCount": 52
},
{
  "_id": 341830,
  "totalCount": 92
},
{
  "_id": 129932,
  "totalCount": 76
},
{
  "_id": 979789,
  "totalCount": 98
},
{
  "_id": 652071,
  "totalCount": 67
},
{
  "_id": 97487,
  "totalCount": 89
},
{
  "_id": 972116,
  "totalCount": 100
},
{
  "_id": 593963,
  "totalCount": 100
},
{
  "_id": 131371,
  "totalCount": 75
},
{
  "_id": 271186,
  "totalCount": 60
},
{
  "_id": 462501,
  "totalCount": 77
},
{
  "_id": 876702,
  "totalCount": 59
},
{
  "_id": 635729,
  "totalCount": 73
},
{
  "_id": 607567,
  "totalCount": 64
},
{
  "_id": 358213,
  "totalCount": 89
},
{
  "_id": 591026,
  "totalCount": 63
},
{
  "_id": 740604,
  "totalCount": 97
},
{
  "_id": 943953,
  "totalCount": 62
},
{
  "_id": 109710,
  "totalCount": 53
},
{
  "_id": 921410,
  "totalCount": 67
},
{
  "_id": 229899,
  "totalCount": 82
},
{
  "_id": 616602,
  "totalCount": 95
},
{
  "_id": 741476,
  "totalCount": 85
},
{
  "_id": 432388,
  "totalCount": 57
},
{
  "_id": 775690,
  "totalCount": 58
},
{
  "_id": 725209,
  "totalCount": 84
},
{
  "_id": 301176,
  "totalCount": 56
},
{
  "_id": 459245,
  "totalCount": 98
},
{
  "_id": 529190,
  "totalCount": 60
},
{
  "_id": 103659,
  "totalCount": 60
},
{
  "_id": 472050,
  "totalCount": 79
},
{
  "_id": 429604,
  "totalCount": 86
},
{
  "_id": 71148,
  "totalCount": 99
},
{
  "_id": 795909,
  "totalCount": 78
},
{
  "_id": 428110,
  "totalCount": 58
},
{
  "_id": 833317,
  "totalCount": 67
},
{
  "_id": 71674,
  "totalCount": 82
},
{
  "_id": 306033,
  "totalCount": 80
},
{
  "_id": 450464,
  "totalCount": 87
},
{
  "_id": 271554,
  "totalCount": 96
},
{
  "_id": 591839,
  "totalCount": 64
},
{
  "_id": 89466,
  "totalCount": 90
},
{
  "_id": 265264,
  "totalCount": 56
},
{
  "_id": 527745,
  "totalCount": 87
},
{
  "_id": 532811,
  "totalCount": 87
},
{
  "_id": 856354,
  "totalCount": 67
},
{
  "_id": 156715,
  "totalCount": 98
},
{
  "_id": 446747,
  "totalCount": 52
},
{
  "_id": 163788,
  "totalCount": 99
},
{
  "_id": 886274,
  "totalCount": 75
},
{
  "_id": 571311,
  "totalCount": 89
},
{
  "_id": 986996,
  "totalCount": 66
},
{
  "_id": 884849,
  "totalCount": 65
},
{
  "_id": 429282,
  "totalCount": 90
},
{
  "_id": 568788,
  "totalCount": 81
},
{
  "_id": 973364,
  "totalCount": 55
},
{
  "_id": 863889,
  "totalCount": 60
},
{
  "_id": 436071,
  "totalCount": 81
},
{
  "_id": 160912,
  "totalCount": 68
},
{
  "_id": 422649,
  "totalCount": 74
},
{
  "_id": 818687,
  "totalCount": 57
},
{
  "_id": 608510,
  "totalCount": 58
},
{
  "_id": 876756,
  "totalCount": 79
},
{
  "_id": 327655,
  "totalCount": 58
},
{
  "_id": 847533,
  "totalCount": 83
},
{
  "_id": 292438,
  "totalCount": 77
},
{
  "_id": 891045,
  "totalCount": 62
},
{
  "_id": 523931,
  "totalCount": 95
},
{
  "_id": 408143,
  "totalCount": 100
},
{
  "_id": 950438,
  "totalCount": 72
},
{
  "_id": 385747,
  "totalCount": 63
},
{
  "_id": 868245,
  "totalCount": 53
},
{
  "_id": 175894,
  "totalCount": 96
},
{
  "_id": 612105,
  "totalCount": 81
},
{
  "_id": 454704,
  "totalCount": 59
},
{
  "_id": 457709,
  "totalCount": 88
},
{
  "_id": 226865,
  "totalCount": 53
},
{
  "_id": 991412,
  "totalCount": 63
},
{
  "_id": 586395,
  "totalCount": 95
},
{
  "_id": 952430,
  "totalCount": 71
},
{
  "_id": 166084,
  "totalCount": 73
},
{
  "_id": 623185,
  "totalCount": 80
},
{
  "_id": 265053,
  "totalCount": 94
},
{
  "_id": 494340,
  "totalCount": 67
},
{
  "_id": 598525,
  "totalCount": 89
},
{
  "_id": 581161,
  "totalCount": 55
},
{
  "_id": 109139,
  "totalCount": 80
},
{
  "_id": 389592,
  "totalCount": 70
},
{
  "_id": 307731,
  "totalCount": 83
},
{
  "_id": 921942,
  "totalCount": 96
},
{
  "_id": 386231,
  "totalCount": 76
},
{
  "_id": 138703,
  "totalCount": 94
},
{
  "_id": 683382,
  "totalCount": 93
},
{
  "_id": 320075,
  "totalCount": 92
},
{
  "_id": 784910,
  "totalCount": 76
},
{
  "_id": 300446,
  "totalCount": 68
},
{
  "_id": 317931,
  "totalCount": 91
},
{
  "_id": 851281,
  "totalCount": 75
},
{
  "_id": 174471,
  "totalCount": 78
},
{
  "_id": 398775,
  "totalCount": 59
},
{
  "_id": 881424,
  "totalCount": 93
},
{
  "_id": 891056,
  "totalCount": 83
},
{
  "_id": 209363,
  "totalCount": 56
},
{
  "_id": 895913,
  "totalCount": 84
},
{
  "_id": 147275,
  "totalCount": 83
},
{
  "_id": 876196,
  "totalCount": 69
},
{
  "_id": 482653,
  "totalCount": 66
},
{
  "_id": 666856,
  "totalCount": 81
},
{
  "_id": 262642,
  "totalCount": 95
},
{
  "_id": 451764,
  "totalCount": 52
},
{
  "_id": 120472,
  "totalCount": 88
},
{
  "_id": 467666,
  "totalCount": 71
},
{
  "_id": 59819,
  "totalCount": 84
},
{
  "_id": 626698,
  "totalCount": 72
},
{
  "_id": 774952,
  "totalCount": 63
},
{
  "_id": 433811,
  "totalCount": 75
},
{
  "_id": 747054,
  "totalCount": 90
},
{
  "_id": 495198,
  "totalCount": 58
},
{
  "_id": 179020,
  "totalCount": 83
},
{
  "_id": 333642,
  "totalCount": 88
},
{
  "_id": 210670,
  "totalCount": 60
},
{
  "_id": 382550,
  "totalCount": 88
},
{
  "_id": 987355,
  "totalCount": 80
},
{
  "_id": 447644,
  "totalCount": 58
},
{
  "_id": 401048,
  "totalCount": 55
},
{
  "_id": 448325,
  "totalCount": 64
},
{
  "_id": 768875,
  "totalCount": 59
},
{
  "_id": 391557,
  "totalCount": 82
},
{
  "_id": 412013,
  "totalCount": 86
},
{
  "_id": 95826,
  "totalCount": 88
},
{
  "_id": 154492,
  "totalCount": 77
},
{
  "_id": 136137,
  "totalCount": 51
},
{
  "_id": 275187,
  "totalCount": 73
},
{
  "_id": 426335,
  "totalCount": 54
},
{
  "_id": 858473,
  "totalCount": 58
},
{
  "_id": 957207,
  "totalCount": 67
},
{
  "_id": 62872,
  "totalCount": 54
},
{
  "_id": 966629,
  "totalCount": 95
},
{
  "_id": 451189,
  "totalCount": 69
},
{
  "_id": 599752,
  "totalCount": 77
},
{
  "_id": 328105,
  "totalCount": 57
},
{
  "_id": 359211,
  "totalCount": 87
},
{
  "_id": 659017,
  "totalCount": 85
},
{
  "_id": 198855,
  "totalCount": 55
},
{
  "_id": 497929,
  "totalCount": 61
},
{
  "_id": 225930,
  "totalCount": 88
},
{
  "_id": 388950,
  "totalCount": 78
},
{
  "_id": 429071,
  "totalCount": 97
},
{
  "_id": 351905,
  "totalCount": 58
},
{
  "_id": 452686,
  "totalCount": 62
},
{
  "_id": 312942,
  "totalCount": 61
},
{
  "_id": 470078,
  "totalCount": 93
},
{
  "_id": 328686,
  "totalCount": 58
},
{
  "_id": 847434,
  "totalCount": 66
},
{
  "_id": 757619,
  "totalCount": 75
},
{
  "_id": 463119,
  "totalCount": 71
},
{
  "_id": 188293,
  "totalCount": 64
},
{
  "_id": 69218,
  "totalCount": 70
},
{
  "_id": 736396,
  "totalCount": 77
},
{
  "_id": 193228,
  "totalCount": 74
},
{
  "_id": 272399,
  "totalCount": 64
},
{
  "_id": 771935,
  "totalCount": 76
},
{
  "_id": 916626,
  "totalCount": 82
},
{
  "_id": 90117,
  "totalCount": 92
},
{
  "_id": 664533,
  "totalCount": 82
},
{
  "_id": 375872,
  "totalCount": 94
},
{
  "_id": 914197,
  "totalCount": 52
},
{
  "_id": 671035,
  "totalCount": 96
},
{
  "_id": 855057,
  "totalCount": 79
},
{
  "_id": 218214,
  "totalCount": 81
},
{
  "_id": 415928,
  "totalCount": 66
},
{
  "_id": 616103,
  "totalCount": 63
},
{
  "_id": 55104,
  "totalCount": 78
},
{
  "_id": 371349,
  "totalCount": 86
},
{
  "_id": 833412,
  "totalCount": 77
},
{
  "_id": 356073,
  "totalCount": 53
},
{
  "_id": 446093,
  "totalCount": 82
},
{
  "_id": 962115,
  "totalCount": 88
},
{
  "_id": 650995,
  "totalCount": 66
},
{
  "_id": 648021,
  "totalCount": 93
},
{
  "_id": 822672,
  "totalCount": 95
},
{
  "_id": 630581,
  "totalCount": 80
},
{
  "_id": 759079,
  "totalCount": 60
},
{
  "_id": 698136,
  "totalCount": 78
},
{
  "_id": 558349,
  "totalCount": 53
},
{
  "_id": 651827,
  "totalCount": 91
},
{
  "_id": 744220,
  "totalCount": 86
},
{
  "_id": 563516,
  "totalCount": 67
},
{
  "_id": 884552,
  "totalCount": 90
},
{
  "_id": 764007,
  "totalCount": 92
},
{
  "_id": 515560,
  "totalCount": 99
},
{
  "_id": 130870,
  "totalCount": 76
},
{
  "_id": 223693,
  "totalCount": 67
},
{
  "_id": 840171,
  "totalCount": 79
},
{
  "_id": 380955,
  "totalCount": 52
},
{
  "_id": 139687,
  "totalCount": 91
},
{
  "_id": 911207,
  "totalCount": 54
},
{
  "_id": 141868,
  "totalCount": 62
},
{
  "_id": 533756,
  "totalCount": 79
},
{
  "_id": 526731,
  "totalCount": 94
},
{
  "_id": 550456,
  "totalCount": 78
},
{
  "_id": 912196,
  "totalCount": 80
},
{
  "_id": 65661,
  "totalCount": 67
},
{
  "_id": 631593,
  "totalCount": 54
},
{
  "_id": 455365,
  "totalCount": 63
},
{
  "_id": 357823,
  "totalCount": 82
},
{
  "_id": 862214,
  "totalCount": 70
},
{
  "_id": 509009,
  "totalCount": 63
},
{
  "_id": 664029,
  "totalCount": 94
},
{
  "_id": 182094,
  "totalCount": 82
},
{
  "_id": 289795,
  "totalCount": 67
},
{
  "_id": 162572,
  "totalCount": 63
},
{
  "_id": 632303,
  "totalCount": 53
},
{
  "_id": 615233,
  "totalCount": 83
},
{
  "_id": 951849,
  "totalCount": 89
},
{
  "_id": 215284,
  "totalCount": 91
},
{
  "_id": 315164,
  "totalCount": 91
},
{
  "_id": 810947,
  "totalCount": 96
},
{
  "_id": 238687,
  "totalCount": 93
},
{
  "_id": 980639,
  "totalCount": 80
},
{
  "_id": 332179,
  "totalCount": 99
},
{
  "_id": 190959,
  "totalCount": 61
},
{
  "_id": 586861,
  "totalCount": 54
},
{
  "_id": 455692,
  "totalCount": 69
},
{
  "_id": 689102,
  "totalCount": 93
},
{
  "_id": 980867,
  "totalCount": 64
},
{
  "_id": 153460,
  "totalCount": 99
},
{
  "_id": 447044,
  "totalCount": 97
},
{
  "_id": 126668,
  "totalCount": 58
},
{
  "_id": 322023,
  "totalCount": 70
},
{
  "_id": 263864,
  "totalCount": 55
},
{
  "_id": 321208,
  "totalCount": 88
},
{
  "_id": 994562,
  "totalCount": 85
},
{
  "_id": 375655,
  "totalCount": 93
},
{
  "_id": 177004,
  "totalCount": 60
},
{
  "_id": 595194,
  "totalCount": 70
},
{
  "_id": 116508,
  "totalCount": 81
},
{
  "_id": 423202,
  "totalCount": 83
},
{
  "_id": 302149,
  "totalCount": 67
},
{
  "_id": 928506,
  "totalCount": 66
},
{
  "_id": 258443,
  "totalCount": 75
},
{
  "_id": 774388,
  "totalCount": 97
},
{
  "_id": 945366,
  "totalCount": 70
},
{
  "_id": 831465,
  "totalCount": 69
},
{
  "_id": 913332,
  "totalCount": 79
},
{
  "_id": 467651,
  "totalCount": 99
},
{
  "_id": 933986,
  "totalCount": 70
},
{
  "_id": 867364,
  "totalCount": 96
},
{
  "_id": 666556,
  "totalCount": 79
},
{
  "_id": 976021,
  "totalCount": 81
},
{
  "_id": 648052,
  "totalCount": 77
},
{
  "_id": 77397,
  "totalCount": 100
},
{
  "_id": 616016,
  "totalCount": 73
},
{
  "_id": 899684,
  "totalCount": 86
},
{
  "_id": 788012,
  "totalCount": 84
},
{
  "_id": 959435,
  "totalCount": 93
},
{
  "_id": 124977,
  "totalCount": 74
},
{
  "_id": 370854,
  "totalCount": 79
},
{
  "_id": 83355,
  "totalCount": 53
},
{
  "_id": 167939,
  "totalCount": 77
},
{
  "_id": 212219,
  "totalCount": 97
},
{
  "_id": 750828,
  "totalCount": 84
},
{
  "_id": 177799,
  "totalCount": 72
},
{
  "_id": 219169,
  "totalCount": 98
},
{
  "_id": 370583,
  "totalCount": 83
},
{
  "_id": 456867,
  "totalCount": 87
},
{
  "_id": 603062,
  "totalCount": 65
},
{
  "_id": 958411,
  "totalCount": 65
},
{
  "_id": 396044,
  "totalCount": 90
},
{
  "_id": 893678,
  "totalCount": 56
},
{
  "_id": 150321,
  "totalCount": 62
},
{
  "_id": 347313,
  "totalCount": 54
},
{
  "_id": 304450,
  "totalCount": 81
},
{
  "_id": 640857,
  "totalCount": 55
},
{
  "_id": 741049,
  "totalCount": 88
},
{
  "_id": 278603,
  "totalCount": 83
},
{
  "_id": 397600,
  "totalCount": 67
},
{
  "_id": 278866,
  "totalCount": 100
},
{
  "_id": 895434,
  "totalCount": 73
},
{
  "_id": 412983,
  "totalCount": 94
},
{
  "_id": 550665,
  "totalCount": 64
},
{
  "_id": 163269,
  "totalCount": 65
},
{
  "_id": 59768,
  "totalCount": 98
},
{
  "_id": 711252,
  "totalCount": 68
},
{
  "_id": 737334,
  "totalCount": 57
},
{
  "_id": 879203,
  "totalCount": 84
},
{
  "_id": 514152,
  "totalCount": 53
},
{
  "_id": 873264,
  "totalCount": 63
},
{
  "_id": 870028,
  "totalCount": 86
},
{
  "_id": 774172,
  "totalCount": 68
},
{
  "_id": 470650,
  "totalCount": 85
},
{
  "_id": 770312,
  "totalCount": 55
},
{
  "_id": 671031,
  "totalCount": 99
},
{
  "_id": 785786,
  "totalCount": 82
},
{
  "_id": 987501,
  "totalCount": 93
},
{
  "_id": 845284,
  "totalCount": 100
},
{
  "_id": 950726,
  "totalCount": 70
},
{
  "_id": 73934,
  "totalCount": 53
},
{
  "_id": 923502,
  "totalCount": 90
},
{
  "_id": 637133,
  "totalCount": 51
},
{
  "_id": 874631,
  "totalCount": 59
},
{
  "_id": 892478,
  "totalCount": 99
},
{
  "_id": 614528,
  "totalCount": 74
},
{
  "_id": 205355,
  "totalCount": 53
},
{
  "_id": 913758,
  "totalCount": 84
},
{
  "_id": 265862,
  "totalCount": 97
},
{
  "_id": 285957,
  "totalCount": 67
},
{
  "_id": 225602,
  "totalCount": 88
},
{
  "_id": 727837,
  "totalCount": 76
},
{
  "_id": 360655,
  "totalCount": 81
},
{
  "_id": 659814,
  "totalCount": 92
},
{
  "_id": 373169,
  "totalCount": 93
},
{
  "_id": 731178,
  "totalCount": 81
},
{
  "_id": 436026,
  "totalCount": 56
},
{
  "_id": 892096,
  "totalCount": 57
}]